{
  "schemaVersion": 1,
  "id": "celecraft",
  "version": "${version}",

  "name": "Celecraft",
  "description": "Who wants to climb Celeste in Minecraft?!",
  "authors": [
    "WhitrayHB"
  ],
  "contact": {
    "homepage": "https://fabricmc.net/",
    "sources": "https://github.com/FabricMC/fabric-example-mod"
  },

  "license": "LGPL-3.0",
  "icon": "assets/celecraft/icon.png",

  "environment": "*",
  "entrypoints": {
    "main": [
      "cn.whitrayhb.celecraft.CelecraftMain"
    ],
    "client": [
      "cn.whitrayhb.celecraft.CelecraftClient"
    ],
    "server": [
      "cn.whitrayhb.celecraft.CelecraftServer"
    ]
  },
  "mixins": [
    "celecraft.mixins.json"
  ],

  "depends": {
    "fabricloader": ">=0.11.3",
    "fabric": "*",
    "minecraft": "1.18.x",
    "java": ">=17",
    "fabric-key-binding-api-v1": "*"
  },
  "suggests": {
    "another-mod": "*"
  }
}
